<?xml version="1.0" encoding="utf-8" ?><dwsync><file name="mhous02.jpg" server="www.asvstudio.com//public_html/" local="3708263068" remote="3708287940" Dst="-1" /><file name="mhous01.jpg" server="www.asvstudio.com//public_html/" local="3708262990" remote="3708287940" Dst="-1" /><file name="mhous04.jpg" server="www.asvstudio.com//public_html/" local="3708265578" remote="3708287940" Dst="-1" /><file name="mhous03.jpg" server="www.asvstudio.com//public_html/" local="3708263118" remote="3708287940" Dst="-1" /><file name="mhous05.jpg" server="www.asvstudio.com//public_html/" local="3708265630" remote="3708287940" Dst="-1" /><file name="mhous07.jpg" server="www.asvstudio.com//public_html/" local="3708265738" remote="3708287940" Dst="-1" /><file name="mhous08.jpg" server="www.asvstudio.com//public_html/" local="3708265792" remote="3708287940" Dst="-1" /><file name="mhous06.jpg" server="www.asvstudio.com//public_html/" local="3708265678" remote="3708287940" Dst="-1" /><file name="mhous11.jpg" server="www.asvstudio.com//public_html/" local="3708265966" remote="3708287940" Dst="-1" /><file name="mhous09.jpg" server="www.asvstudio.com//public_html/" local="3708265838" remote="3708287940" Dst="-1" /><file name="mhous10.jpg" server="www.asvstudio.com//public_html/" local="3708265886" remote="3708287940" Dst="-1" /><file name="mhous13.jpg" server="www.asvstudio.com//public_html/" local="3708266078" remote="3708287940" Dst="-1" /><file name="mhous14.jpg" server="www.asvstudio.com//public_html/" local="3708266130" remote="3708287940" Dst="-1" /><file name="mhous12.jpg" server="www.asvstudio.com//public_html/" local="3708266024" remote="3708287940" Dst="-1" /><file name="mhous15.jpg" server="www.asvstudio.com//public_html/" local="3708266180" remote="3708287940" Dst="-1" /><file name="mhous17.jpg" server="www.asvstudio.com//public_html/" local="3708266318" remote="3708287940" Dst="-1" /><file name="mhous16.jpg" server="www.asvstudio.com//public_html/" local="3708266270" remote="3708287940" Dst="-1" /><file name="mhous18.jpg" server="www.asvstudio.com//public_html/" local="3708266360" remote="3708287940" Dst="-1" /><file name="mhous20.jpg" server="www.asvstudio.com//public_html/" local="3708266456" remote="3708287940" Dst="-1" /><file name="mhous19.jpg" server="www.asvstudio.com//public_html/" local="3708266408" remote="3708287940" Dst="-1" /><file name="mhous23.jpg" server="www.asvstudio.com//public_html/" local="3708266596" remote="3708287940" Dst="-1" /><file name="mhous21.jpg" server="www.asvstudio.com//public_html/" local="3708266500" remote="3708287940" Dst="-1" /><file name="mhous22.jpg" server="www.asvstudio.com//public_html/" local="3708266548" remote="3708287940" Dst="-1" /><file name="mhous25.jpg" server="www.asvstudio.com//public_html/" local="3708266688" remote="3708287940" Dst="-1" /><file name="mhous26.jpg" server="www.asvstudio.com//public_html/" local="3708266734" remote="3708287940" Dst="-1" /><file name="mhous24.jpg" server="www.asvstudio.com//public_html/" local="3708266644" remote="3708287940" Dst="-1" /><file name="mhous27.jpg" server="www.asvstudio.com//public_html/" local="3708266778" remote="3708287940" Dst="-1" /><file name="mhous29.jpg" server="www.asvstudio.com//public_html/" local="3708266876" remote="3708287940" Dst="-1" /><file name="mhous28.jpg" server="www.asvstudio.com//public_html/" local="3708266828" remote="3708287940" Dst="-1" /></dwsync>